ppchemistrysdk_cli/__init__.py
ppchemistrysdk_cli/core.py
ppchemistrysdk_cli/main.py
ppchemistrysdk_cli-0.1.0.dist-info/entry_points.txt
ppchemistrysdk_cli-0.1.0.dist-info/WHEEL
ppchemistrysdk_cli-0.1.0.dist-info/METADATA
ppchemistrysdk_cli-0.1.0.dist-info/RECORD
