Metadata-Version: 2.1
Name: ppchemistrysdk-cli
Version: 0.1.0
Summary: 
Author: Eike Caldeweyher
Author-email: e.caldeweyher@gmail.com
Requires-Python: >=3.8,<4.0
Classifier: Programming Language :: Python :: 3
Classifier: Programming Language :: Python :: 3.10
Classifier: Programming Language :: Python :: 3.8
Classifier: Programming Language :: Python :: 3.9
Requires-Dist: numpy (>=1.22.4,<2.0.0)
Requires-Dist: typer[all] (>=0.4.1,<0.5.0)
